{
  "_meta": {
    "files": {
      "cia": {
        "path": "hardware/cia.i",
        "version": "cia.i 39.1 (18.9.92)"
      },
      "custom": {
        "path": "hardware/custom.i",
        "version": "custom.i 39.1 (18.9.92)"
      }
    },
    "include_dir": "hardware/",
    "source": "NDK hardware includes"
  },
  "registers": [
    {
      "base_symbol": "_custom",
      "cpu_address": "0xDFF000",
      "family": "custom",
      "include": "hardware/custom.i",
      "offset": "0x000",
      "symbols": [
        "bltddat"
      ]
    },
    {
      "base_symbol": "_custom",
      "cpu_address": "0xDFF002",
      "family": "custom",
      "include": "hardware/custom.i",
      "offset": "0x002",
      "symbols": [
        "dmaconr"
      ]
    },
    {
      "base_symbol": "_custom",
      "cpu_address": "0xDFF004",
      "family": "custom",
      "include": "hardware/custom.i",
      "offset": "0x004",
      "symbols": [
        "vposr"
      ]
    },
    {
      "base_symbol": "_custom",
      "cpu_address": "0xDFF006",
      "family": "custom",
      "include": "hardware/custom.i",
      "offset": "0x006",
      "symbols": [
        "vhposr"
      ]
    },
    {
      "base_symbol": "_custom",
      "cpu_address": "0xDFF008",
      "family": "custom",
      "include": "hardware/custom.i",
      "offset": "0x008",
      "symbols": [
        "dskdatr"
      ]
    },
    {
      "base_symbol": "_custom",
      "cpu_address": "0xDFF00A",
      "family": "custom",
      "include": "hardware/custom.i",
      "offset": "0x00A",
      "symbols": [
        "joy0dat"
      ]
    },
    {
      "base_symbol": "_custom",
      "cpu_address": "0xDFF00C",
      "family": "custom",
      "include": "hardware/custom.i",
      "offset": "0x00C",
      "symbols": [
        "joy1dat"
      ]
    },
    {
      "base_symbol": "_custom",
      "cpu_address": "0xDFF00E",
      "family": "custom",
      "include": "hardware/custom.i",
      "offset": "0x00E",
      "symbols": [
        "clxdat"
      ]
    },
    {
      "base_symbol": "_custom",
      "cpu_address": "0xDFF010",
      "family": "custom",
      "include": "hardware/custom.i",
      "offset": "0x010",
      "symbols": [
        "adkconr"
      ]
    },
    {
      "base_symbol": "_custom",
      "cpu_address": "0xDFF012",
      "family": "custom",
      "include": "hardware/custom.i",
      "offset": "0x012",
      "symbols": [
        "pot0dat"
      ]
    },
    {
      "base_symbol": "_custom",
      "cpu_address": "0xDFF014",
      "family": "custom",
      "include": "hardware/custom.i",
      "offset": "0x014",
      "symbols": [
        "pot1dat"
      ]
    },
    {
      "base_symbol": "_custom",
      "cpu_address": "0xDFF016",
      "family": "custom",
      "include": "hardware/custom.i",
      "offset": "0x016",
      "symbols": [
        "potinp"
      ]
    },
    {
      "base_symbol": "_custom",
      "cpu_address": "0xDFF018",
      "family": "custom",
      "include": "hardware/custom.i",
      "offset": "0x018",
      "symbols": [
        "serdatr"
      ]
    },
    {
      "base_symbol": "_custom",
      "cpu_address": "0xDFF01A",
      "family": "custom",
      "include": "hardware/custom.i",
      "offset": "0x01A",
      "symbols": [
        "dskbytr"
      ]
    },
    {
      "base_symbol": "_custom",
      "cpu_address": "0xDFF01C",
      "family": "custom",
      "include": "hardware/custom.i",
      "offset": "0x01C",
      "symbols": [
        "intenar"
      ]
    },
    {
      "base_symbol": "_custom",
      "cpu_address": "0xDFF01E",
      "family": "custom",
      "include": "hardware/custom.i",
      "offset": "0x01E",
      "symbols": [
        "intreqr"
      ]
    },
    {
      "base_symbol": "_custom",
      "cpu_address": "0xDFF020",
      "family": "custom",
      "include": "hardware/custom.i",
      "offset": "0x020",
      "symbols": [
        "dskpt"
      ]
    },
    {
      "base_symbol": "_custom",
      "cpu_address": "0xDFF024",
      "family": "custom",
      "include": "hardware/custom.i",
      "offset": "0x024",
      "symbols": [
        "dsklen"
      ]
    },
    {
      "base_symbol": "_custom",
      "cpu_address": "0xDFF026",
      "family": "custom",
      "include": "hardware/custom.i",
      "offset": "0x026",
      "symbols": [
        "dskdat"
      ]
    },
    {
      "base_symbol": "_custom",
      "cpu_address": "0xDFF028",
      "family": "custom",
      "include": "hardware/custom.i",
      "offset": "0x028",
      "symbols": [
        "refptr"
      ]
    },
    {
      "base_symbol": "_custom",
      "cpu_address": "0xDFF02A",
      "family": "custom",
      "include": "hardware/custom.i",
      "offset": "0x02A",
      "symbols": [
        "vposw"
      ]
    },
    {
      "base_symbol": "_custom",
      "cpu_address": "0xDFF02C",
      "family": "custom",
      "include": "hardware/custom.i",
      "offset": "0x02C",
      "symbols": [
        "vhposw"
      ]
    },
    {
      "base_symbol": "_custom",
      "cpu_address": "0xDFF02E",
      "family": "custom",
      "include": "hardware/custom.i",
      "offset": "0x02E",
      "symbols": [
        "copcon"
      ]
    },
    {
      "base_symbol": "_custom",
      "cpu_address": "0xDFF030",
      "family": "custom",
      "include": "hardware/custom.i",
      "offset": "0x030",
      "symbols": [
        "serdat"
      ]
    },
    {
      "base_symbol": "_custom",
      "cpu_address": "0xDFF032",
      "family": "custom",
      "include": "hardware/custom.i",
      "offset": "0x032",
      "symbols": [
        "serper"
      ]
    },
    {
      "base_symbol": "_custom",
      "cpu_address": "0xDFF034",
      "family": "custom",
      "include": "hardware/custom.i",
      "offset": "0x034",
      "symbols": [
        "potgo"
      ]
    },
    {
      "base_symbol": "_custom",
      "cpu_address": "0xDFF036",
      "family": "custom",
      "include": "hardware/custom.i",
      "offset": "0x036",
      "symbols": [
        "joytest"
      ]
    },
    {
      "base_symbol": "_custom",
      "cpu_address": "0xDFF038",
      "family": "custom",
      "include": "hardware/custom.i",
      "offset": "0x038",
      "symbols": [
        "strequ"
      ]
    },
    {
      "base_symbol": "_custom",
      "cpu_address": "0xDFF03A",
      "family": "custom",
      "include": "hardware/custom.i",
      "offset": "0x03A",
      "symbols": [
        "strvbl"
      ]
    },
    {
      "base_symbol": "_custom",
      "cpu_address": "0xDFF03C",
      "family": "custom",
      "include": "hardware/custom.i",
      "offset": "0x03C",
      "symbols": [
        "strhor"
      ]
    },
    {
      "base_symbol": "_custom",
      "cpu_address": "0xDFF03E",
      "family": "custom",
      "include": "hardware/custom.i",
      "offset": "0x03E",
      "symbols": [
        "strlong"
      ]
    },
    {
      "base_symbol": "_custom",
      "cpu_address": "0xDFF040",
      "family": "custom",
      "include": "hardware/custom.i",
      "offset": "0x040",
      "symbols": [
        "bltcon0"
      ]
    },
    {
      "base_symbol": "_custom",
      "cpu_address": "0xDFF042",
      "family": "custom",
      "include": "hardware/custom.i",
      "offset": "0x042",
      "symbols": [
        "bltcon1"
      ]
    },
    {
      "base_symbol": "_custom",
      "cpu_address": "0xDFF044",
      "family": "custom",
      "include": "hardware/custom.i",
      "offset": "0x044",
      "symbols": [
        "bltafwm"
      ]
    },
    {
      "base_symbol": "_custom",
      "cpu_address": "0xDFF046",
      "family": "custom",
      "include": "hardware/custom.i",
      "offset": "0x046",
      "symbols": [
        "bltalwm"
      ]
    },
    {
      "base_symbol": "_custom",
      "cpu_address": "0xDFF048",
      "family": "custom",
      "include": "hardware/custom.i",
      "offset": "0x048",
      "symbols": [
        "bltcpt"
      ]
    },
    {
      "base_symbol": "_custom",
      "cpu_address": "0xDFF04C",
      "family": "custom",
      "include": "hardware/custom.i",
      "offset": "0x04C",
      "symbols": [
        "bltbpt"
      ]
    },
    {
      "base_symbol": "_custom",
      "cpu_address": "0xDFF050",
      "family": "custom",
      "include": "hardware/custom.i",
      "offset": "0x050",
      "symbols": [
        "bltapt"
      ]
    },
    {
      "base_symbol": "_custom",
      "cpu_address": "0xDFF054",
      "family": "custom",
      "include": "hardware/custom.i",
      "offset": "0x054",
      "symbols": [
        "bltdpt"
      ]
    },
    {
      "base_symbol": "_custom",
      "cpu_address": "0xDFF058",
      "family": "custom",
      "include": "hardware/custom.i",
      "offset": "0x058",
      "symbols": [
        "bltsize"
      ]
    },
    {
      "base_symbol": "_custom",
      "cpu_address": "0xDFF05B",
      "family": "custom",
      "include": "hardware/custom.i",
      "offset": "0x05B",
      "symbols": [
        "bltcon0l"
      ]
    },
    {
      "base_symbol": "_custom",
      "cpu_address": "0xDFF05C",
      "family": "custom",
      "include": "hardware/custom.i",
      "offset": "0x05C",
      "symbols": [
        "bltsizv"
      ]
    },
    {
      "base_symbol": "_custom",
      "cpu_address": "0xDFF05E",
      "family": "custom",
      "include": "hardware/custom.i",
      "offset": "0x05E",
      "symbols": [
        "bltsizh"
      ]
    },
    {
      "base_symbol": "_custom",
      "cpu_address": "0xDFF060",
      "family": "custom",
      "include": "hardware/custom.i",
      "offset": "0x060",
      "symbols": [
        "bltcmod"
      ]
    },
    {
      "base_symbol": "_custom",
      "cpu_address": "0xDFF062",
      "family": "custom",
      "include": "hardware/custom.i",
      "offset": "0x062",
      "symbols": [
        "bltbmod"
      ]
    },
    {
      "base_symbol": "_custom",
      "cpu_address": "0xDFF064",
      "family": "custom",
      "include": "hardware/custom.i",
      "offset": "0x064",
      "symbols": [
        "bltamod"
      ]
    },
    {
      "base_symbol": "_custom",
      "cpu_address": "0xDFF066",
      "family": "custom",
      "include": "hardware/custom.i",
      "offset": "0x066",
      "symbols": [
        "bltdmod"
      ]
    },
    {
      "base_symbol": "_custom",
      "cpu_address": "0xDFF070",
      "family": "custom",
      "include": "hardware/custom.i",
      "offset": "0x070",
      "symbols": [
        "bltcdat"
      ]
    },
    {
      "base_symbol": "_custom",
      "cpu_address": "0xDFF072",
      "family": "custom",
      "include": "hardware/custom.i",
      "offset": "0x072",
      "symbols": [
        "bltbdat"
      ]
    },
    {
      "base_symbol": "_custom",
      "cpu_address": "0xDFF074",
      "family": "custom",
      "include": "hardware/custom.i",
      "offset": "0x074",
      "symbols": [
        "bltadat"
      ]
    },
    {
      "base_symbol": "_custom",
      "cpu_address": "0xDFF07C",
      "family": "custom",
      "include": "hardware/custom.i",
      "offset": "0x07C",
      "symbols": [
        "deniseid"
      ]
    },
    {
      "base_symbol": "_custom",
      "cpu_address": "0xDFF07E",
      "family": "custom",
      "include": "hardware/custom.i",
      "offset": "0x07E",
      "symbols": [
        "dsksync"
      ]
    },
    {
      "base_symbol": "_custom",
      "cpu_address": "0xDFF080",
      "family": "custom",
      "include": "hardware/custom.i",
      "offset": "0x080",
      "symbols": [
        "cop1lc"
      ]
    },
    {
      "base_symbol": "_custom",
      "cpu_address": "0xDFF084",
      "family": "custom",
      "include": "hardware/custom.i",
      "offset": "0x084",
      "symbols": [
        "cop2lc"
      ]
    },
    {
      "base_symbol": "_custom",
      "cpu_address": "0xDFF088",
      "family": "custom",
      "include": "hardware/custom.i",
      "offset": "0x088",
      "symbols": [
        "copjmp1"
      ]
    },
    {
      "base_symbol": "_custom",
      "cpu_address": "0xDFF08A",
      "family": "custom",
      "include": "hardware/custom.i",
      "offset": "0x08A",
      "symbols": [
        "copjmp2"
      ]
    },
    {
      "base_symbol": "_custom",
      "cpu_address": "0xDFF08C",
      "family": "custom",
      "include": "hardware/custom.i",
      "offset": "0x08C",
      "symbols": [
        "copins"
      ]
    },
    {
      "base_symbol": "_custom",
      "cpu_address": "0xDFF08E",
      "family": "custom",
      "include": "hardware/custom.i",
      "offset": "0x08E",
      "symbols": [
        "diwstrt"
      ]
    },
    {
      "base_symbol": "_custom",
      "cpu_address": "0xDFF090",
      "family": "custom",
      "include": "hardware/custom.i",
      "offset": "0x090",
      "symbols": [
        "diwstop"
      ]
    },
    {
      "base_symbol": "_custom",
      "cpu_address": "0xDFF092",
      "family": "custom",
      "include": "hardware/custom.i",
      "offset": "0x092",
      "symbols": [
        "ddfstrt"
      ]
    },
    {
      "base_symbol": "_custom",
      "cpu_address": "0xDFF094",
      "family": "custom",
      "include": "hardware/custom.i",
      "offset": "0x094",
      "symbols": [
        "ddfstop"
      ]
    },
    {
      "base_symbol": "_custom",
      "cpu_address": "0xDFF096",
      "family": "custom",
      "include": "hardware/custom.i",
      "offset": "0x096",
      "symbols": [
        "dmacon"
      ]
    },
    {
      "base_symbol": "_custom",
      "cpu_address": "0xDFF098",
      "family": "custom",
      "include": "hardware/custom.i",
      "offset": "0x098",
      "symbols": [
        "clxcon"
      ]
    },
    {
      "base_symbol": "_custom",
      "cpu_address": "0xDFF09A",
      "family": "custom",
      "include": "hardware/custom.i",
      "offset": "0x09A",
      "symbols": [
        "intena"
      ]
    },
    {
      "base_symbol": "_custom",
      "cpu_address": "0xDFF09C",
      "family": "custom",
      "include": "hardware/custom.i",
      "offset": "0x09C",
      "symbols": [
        "intreq"
      ]
    },
    {
      "base_symbol": "_custom",
      "cpu_address": "0xDFF09E",
      "family": "custom",
      "include": "hardware/custom.i",
      "offset": "0x09E",
      "symbols": [
        "adkcon"
      ]
    },
    {
      "base_symbol": "_custom",
      "cpu_address": "0xDFF0A0",
      "family": "custom",
      "include": "hardware/custom.i",
      "offset": "0x0A0",
      "symbols": [
        "aud0",
        "aud"
      ]
    },
    {
      "base_symbol": "_custom",
      "cpu_address": "0xDFF0B0",
      "family": "custom",
      "include": "hardware/custom.i",
      "offset": "0x0B0",
      "symbols": [
        "aud1"
      ]
    },
    {
      "base_symbol": "_custom",
      "cpu_address": "0xDFF0C0",
      "family": "custom",
      "include": "hardware/custom.i",
      "offset": "0x0C0",
      "symbols": [
        "aud2"
      ]
    },
    {
      "base_symbol": "_custom",
      "cpu_address": "0xDFF0D0",
      "family": "custom",
      "include": "hardware/custom.i",
      "offset": "0x0D0",
      "symbols": [
        "aud3"
      ]
    },
    {
      "base_symbol": "_custom",
      "cpu_address": "0xDFF0E0",
      "family": "custom",
      "include": "hardware/custom.i",
      "offset": "0x0E0",
      "symbols": [
        "bplpt"
      ]
    },
    {
      "base_symbol": "_custom",
      "cpu_address": "0xDFF100",
      "family": "custom",
      "include": "hardware/custom.i",
      "offset": "0x100",
      "symbols": [
        "bplcon0"
      ]
    },
    {
      "base_symbol": "_custom",
      "cpu_address": "0xDFF102",
      "family": "custom",
      "include": "hardware/custom.i",
      "offset": "0x102",
      "symbols": [
        "bplcon1"
      ]
    },
    {
      "base_symbol": "_custom",
      "cpu_address": "0xDFF104",
      "family": "custom",
      "include": "hardware/custom.i",
      "offset": "0x104",
      "symbols": [
        "bplcon2"
      ]
    },
    {
      "base_symbol": "_custom",
      "cpu_address": "0xDFF106",
      "family": "custom",
      "include": "hardware/custom.i",
      "offset": "0x106",
      "symbols": [
        "bplcon3"
      ]
    },
    {
      "base_symbol": "_custom",
      "cpu_address": "0xDFF108",
      "family": "custom",
      "include": "hardware/custom.i",
      "offset": "0x108",
      "symbols": [
        "bpl1mod"
      ]
    },
    {
      "base_symbol": "_custom",
      "cpu_address": "0xDFF10A",
      "family": "custom",
      "include": "hardware/custom.i",
      "offset": "0x10A",
      "symbols": [
        "bpl2mod"
      ]
    },
    {
      "base_symbol": "_custom",
      "cpu_address": "0xDFF10C",
      "family": "custom",
      "include": "hardware/custom.i",
      "offset": "0x10C",
      "symbols": [
        "bplcon4"
      ]
    },
    {
      "base_symbol": "_custom",
      "cpu_address": "0xDFF10E",
      "family": "custom",
      "include": "hardware/custom.i",
      "offset": "0x10E",
      "symbols": [
        "clxcon2"
      ]
    },
    {
      "base_symbol": "_custom",
      "cpu_address": "0xDFF110",
      "family": "custom",
      "include": "hardware/custom.i",
      "offset": "0x110",
      "symbols": [
        "bpldat"
      ]
    },
    {
      "base_symbol": "_custom",
      "cpu_address": "0xDFF120",
      "family": "custom",
      "include": "hardware/custom.i",
      "offset": "0x120",
      "symbols": [
        "sprpt"
      ]
    },
    {
      "base_symbol": "_custom",
      "cpu_address": "0xDFF140",
      "family": "custom",
      "include": "hardware/custom.i",
      "offset": "0x140",
      "symbols": [
        "spr"
      ]
    },
    {
      "base_symbol": "_custom",
      "cpu_address": "0xDFF180",
      "family": "custom",
      "include": "hardware/custom.i",
      "offset": "0x180",
      "symbols": [
        "color"
      ]
    },
    {
      "base_symbol": "_custom",
      "cpu_address": "0xDFF1C0",
      "family": "custom",
      "include": "hardware/custom.i",
      "offset": "0x1C0",
      "symbols": [
        "htotal"
      ]
    },
    {
      "base_symbol": "_custom",
      "cpu_address": "0xDFF1C2",
      "family": "custom",
      "include": "hardware/custom.i",
      "offset": "0x1C2",
      "symbols": [
        "hsstop"
      ]
    },
    {
      "base_symbol": "_custom",
      "cpu_address": "0xDFF1C4",
      "family": "custom",
      "include": "hardware/custom.i",
      "offset": "0x1C4",
      "symbols": [
        "hbstrt"
      ]
    },
    {
      "base_symbol": "_custom",
      "cpu_address": "0xDFF1C6",
      "family": "custom",
      "include": "hardware/custom.i",
      "offset": "0x1C6",
      "symbols": [
        "hbstop"
      ]
    },
    {
      "base_symbol": "_custom",
      "cpu_address": "0xDFF1C8",
      "family": "custom",
      "include": "hardware/custom.i",
      "offset": "0x1C8",
      "symbols": [
        "vtotal"
      ]
    },
    {
      "base_symbol": "_custom",
      "cpu_address": "0xDFF1CA",
      "family": "custom",
      "include": "hardware/custom.i",
      "offset": "0x1CA",
      "symbols": [
        "vsstop"
      ]
    },
    {
      "base_symbol": "_custom",
      "cpu_address": "0xDFF1CC",
      "family": "custom",
      "include": "hardware/custom.i",
      "offset": "0x1CC",
      "symbols": [
        "vbstrt"
      ]
    },
    {
      "base_symbol": "_custom",
      "cpu_address": "0xDFF1CE",
      "family": "custom",
      "include": "hardware/custom.i",
      "offset": "0x1CE",
      "symbols": [
        "vbstop"
      ]
    },
    {
      "base_symbol": "_custom",
      "cpu_address": "0xDFF1D0",
      "family": "custom",
      "include": "hardware/custom.i",
      "offset": "0x1D0",
      "symbols": [
        "sprhstrt"
      ]
    },
    {
      "base_symbol": "_custom",
      "cpu_address": "0xDFF1D2",
      "family": "custom",
      "include": "hardware/custom.i",
      "offset": "0x1D2",
      "symbols": [
        "sprhstop"
      ]
    },
    {
      "base_symbol": "_custom",
      "cpu_address": "0xDFF1D4",
      "family": "custom",
      "include": "hardware/custom.i",
      "offset": "0x1D4",
      "symbols": [
        "bplhstrt"
      ]
    },
    {
      "base_symbol": "_custom",
      "cpu_address": "0xDFF1D6",
      "family": "custom",
      "include": "hardware/custom.i",
      "offset": "0x1D6",
      "symbols": [
        "bplhstop"
      ]
    },
    {
      "base_symbol": "_custom",
      "cpu_address": "0xDFF1D8",
      "family": "custom",
      "include": "hardware/custom.i",
      "offset": "0x1D8",
      "symbols": [
        "hhposw"
      ]
    },
    {
      "base_symbol": "_custom",
      "cpu_address": "0xDFF1DA",
      "family": "custom",
      "include": "hardware/custom.i",
      "offset": "0x1DA",
      "symbols": [
        "hhposr"
      ]
    },
    {
      "base_symbol": "_custom",
      "cpu_address": "0xDFF1DC",
      "family": "custom",
      "include": "hardware/custom.i",
      "offset": "0x1DC",
      "symbols": [
        "beamcon0"
      ]
    },
    {
      "base_symbol": "_custom",
      "cpu_address": "0xDFF1DE",
      "family": "custom",
      "include": "hardware/custom.i",
      "offset": "0x1DE",
      "symbols": [
        "hsstrt"
      ]
    },
    {
      "base_symbol": "_custom",
      "cpu_address": "0xDFF1E0",
      "family": "custom",
      "include": "hardware/custom.i",
      "offset": "0x1E0",
      "symbols": [
        "vsstrt"
      ]
    },
    {
      "base_symbol": "_custom",
      "cpu_address": "0xDFF1E2",
      "family": "custom",
      "include": "hardware/custom.i",
      "offset": "0x1E2",
      "symbols": [
        "hcenter"
      ]
    },
    {
      "base_symbol": "_custom",
      "cpu_address": "0xDFF1E4",
      "family": "custom",
      "include": "hardware/custom.i",
      "offset": "0x1E4",
      "symbols": [
        "diwhigh"
      ]
    },
    {
      "base_symbol": "_custom",
      "cpu_address": "0xDFF1FC",
      "family": "custom",
      "include": "hardware/custom.i",
      "offset": "0x1FC",
      "symbols": [
        "fmode"
      ]
    },
    {
      "base_symbol": "_ciaa",
      "cpu_address": "0xBFE001",
      "family": "ciaa",
      "include": "hardware/cia.i",
      "offset": "0x0000",
      "symbols": [
        "ciapra"
      ]
    },
    {
      "base_symbol": "_ciaa",
      "cpu_address": "0xBFE101",
      "family": "ciaa",
      "include": "hardware/cia.i",
      "offset": "0x0100",
      "symbols": [
        "ciaprb"
      ]
    },
    {
      "base_symbol": "_ciaa",
      "cpu_address": "0xBFE201",
      "family": "ciaa",
      "include": "hardware/cia.i",
      "offset": "0x0200",
      "symbols": [
        "ciaddra"
      ]
    },
    {
      "base_symbol": "_ciaa",
      "cpu_address": "0xBFE301",
      "family": "ciaa",
      "include": "hardware/cia.i",
      "offset": "0x0300",
      "symbols": [
        "ciaddrb"
      ]
    },
    {
      "base_symbol": "_ciaa",
      "cpu_address": "0xBFE401",
      "family": "ciaa",
      "include": "hardware/cia.i",
      "offset": "0x0400",
      "symbols": [
        "ciatalo"
      ]
    },
    {
      "base_symbol": "_ciaa",
      "cpu_address": "0xBFE501",
      "family": "ciaa",
      "include": "hardware/cia.i",
      "offset": "0x0500",
      "symbols": [
        "ciatahi"
      ]
    },
    {
      "base_symbol": "_ciaa",
      "cpu_address": "0xBFE601",
      "family": "ciaa",
      "include": "hardware/cia.i",
      "offset": "0x0600",
      "symbols": [
        "ciatblo"
      ]
    },
    {
      "base_symbol": "_ciaa",
      "cpu_address": "0xBFE701",
      "family": "ciaa",
      "include": "hardware/cia.i",
      "offset": "0x0700",
      "symbols": [
        "ciatbhi"
      ]
    },
    {
      "base_symbol": "_ciaa",
      "cpu_address": "0xBFE801",
      "family": "ciaa",
      "include": "hardware/cia.i",
      "offset": "0x0800",
      "symbols": [
        "ciatodlow"
      ]
    },
    {
      "base_symbol": "_ciaa",
      "cpu_address": "0xBFE901",
      "family": "ciaa",
      "include": "hardware/cia.i",
      "offset": "0x0900",
      "symbols": [
        "ciatodmid"
      ]
    },
    {
      "base_symbol": "_ciaa",
      "cpu_address": "0xBFEA01",
      "family": "ciaa",
      "include": "hardware/cia.i",
      "offset": "0x0A00",
      "symbols": [
        "ciatodhi"
      ]
    },
    {
      "base_symbol": "_ciaa",
      "cpu_address": "0xBFEC01",
      "family": "ciaa",
      "include": "hardware/cia.i",
      "offset": "0x0C00",
      "symbols": [
        "ciasdr"
      ]
    },
    {
      "base_symbol": "_ciaa",
      "cpu_address": "0xBFED01",
      "family": "ciaa",
      "include": "hardware/cia.i",
      "offset": "0x0D00",
      "symbols": [
        "ciaicr"
      ]
    },
    {
      "base_symbol": "_ciaa",
      "cpu_address": "0xBFEE01",
      "family": "ciaa",
      "include": "hardware/cia.i",
      "offset": "0x0E00",
      "symbols": [
        "ciacra"
      ]
    },
    {
      "base_symbol": "_ciaa",
      "cpu_address": "0xBFEF01",
      "family": "ciaa",
      "include": "hardware/cia.i",
      "offset": "0x0F00",
      "symbols": [
        "ciacrb"
      ]
    },
    {
      "base_symbol": "_ciab",
      "cpu_address": "0xBFD000",
      "family": "ciab",
      "include": "hardware/cia.i",
      "offset": "0x0000",
      "symbols": [
        "ciapra"
      ]
    },
    {
      "base_symbol": "_ciab",
      "cpu_address": "0xBFD100",
      "family": "ciab",
      "include": "hardware/cia.i",
      "offset": "0x0100",
      "symbols": [
        "ciaprb"
      ]
    },
    {
      "base_symbol": "_ciab",
      "cpu_address": "0xBFD200",
      "family": "ciab",
      "include": "hardware/cia.i",
      "offset": "0x0200",
      "symbols": [
        "ciaddra"
      ]
    },
    {
      "base_symbol": "_ciab",
      "cpu_address": "0xBFD300",
      "family": "ciab",
      "include": "hardware/cia.i",
      "offset": "0x0300",
      "symbols": [
        "ciaddrb"
      ]
    },
    {
      "base_symbol": "_ciab",
      "cpu_address": "0xBFD400",
      "family": "ciab",
      "include": "hardware/cia.i",
      "offset": "0x0400",
      "symbols": [
        "ciatalo"
      ]
    },
    {
      "base_symbol": "_ciab",
      "cpu_address": "0xBFD500",
      "family": "ciab",
      "include": "hardware/cia.i",
      "offset": "0x0500",
      "symbols": [
        "ciatahi"
      ]
    },
    {
      "base_symbol": "_ciab",
      "cpu_address": "0xBFD600",
      "family": "ciab",
      "include": "hardware/cia.i",
      "offset": "0x0600",
      "symbols": [
        "ciatblo"
      ]
    },
    {
      "base_symbol": "_ciab",
      "cpu_address": "0xBFD700",
      "family": "ciab",
      "include": "hardware/cia.i",
      "offset": "0x0700",
      "symbols": [
        "ciatbhi"
      ]
    },
    {
      "base_symbol": "_ciab",
      "cpu_address": "0xBFD800",
      "family": "ciab",
      "include": "hardware/cia.i",
      "offset": "0x0800",
      "symbols": [
        "ciatodlow"
      ]
    },
    {
      "base_symbol": "_ciab",
      "cpu_address": "0xBFD900",
      "family": "ciab",
      "include": "hardware/cia.i",
      "offset": "0x0900",
      "symbols": [
        "ciatodmid"
      ]
    },
    {
      "base_symbol": "_ciab",
      "cpu_address": "0xBFDA00",
      "family": "ciab",
      "include": "hardware/cia.i",
      "offset": "0x0A00",
      "symbols": [
        "ciatodhi"
      ]
    },
    {
      "base_symbol": "_ciab",
      "cpu_address": "0xBFDC00",
      "family": "ciab",
      "include": "hardware/cia.i",
      "offset": "0x0C00",
      "symbols": [
        "ciasdr"
      ]
    },
    {
      "base_symbol": "_ciab",
      "cpu_address": "0xBFDD00",
      "family": "ciab",
      "include": "hardware/cia.i",
      "offset": "0x0D00",
      "symbols": [
        "ciaicr"
      ]
    },
    {
      "base_symbol": "_ciab",
      "cpu_address": "0xBFDE00",
      "family": "ciab",
      "include": "hardware/cia.i",
      "offset": "0x0E00",
      "symbols": [
        "ciacra"
      ]
    },
    {
      "base_symbol": "_ciab",
      "cpu_address": "0xBFDF00",
      "family": "ciab",
      "include": "hardware/cia.i",
      "offset": "0x0F00",
      "symbols": [
        "ciacrb"
      ]
    }
  ]
}